kronbinations/JIT_Array.py
kronbinations/JIT_kronbinations.py
kronbinations/JIT_kronbinations_load.py
kronbinations/Kron_Array.py
kronbinations/Kron_Fun_Modifier.py
kronbinations/__init__.py
kronbinations/kronbinations.py
kronbinations-1.18.dist-info/LICENSE
kronbinations-1.18.dist-info/METADATA
kronbinations-1.18.dist-info/WHEEL
kronbinations-1.18.dist-info/top_level.txt
kronbinations-1.18.dist-info/RECORD
