Metadata-Version: 2.1
Name: kronbinations
Version: 1.18
Summary: kronbinations is used to remove nested loops and perform parameter sweeps.
Home-page: https://github.com/Ntropic/kronbinations/archive/refs/tags/v1.18.tar.gz
Author: Michael Schilling
Author-email: michael@ntropic.de
Classifier: Programming Language :: Python :: 3
Classifier: License :: OSI Approved :: MIT License
Classifier: Operating System :: OS Independent
Requires-Python: >=3.6
License-File: LICENSE
Requires-Dist: numpy
Requires-Dist: weighted-tqdm
Requires-Dist: pathos
